mptt_urls/__init__.py
django_mptt_urls-2.0.0a1.dist-info/top_level.txt
django_mptt_urls-2.0.0a1.dist-info/DESCRIPTION.rst
django_mptt_urls-2.0.0a1.dist-info/METADATA
django_mptt_urls-2.0.0a1.dist-info/RECORD
django_mptt_urls-2.0.0a1.dist-info/WHEEL
django_mptt_urls-2.0.0a1.dist-info/metadata.json
