Metadata-Version: 2.0
Name: django-mptt-urls
Version: 2.0.0a1
Summary: Django app for creating hierarchical URLs associated with django-MPTT models.
Home-page: https://github.com/c0ntribut0r/django-mptt-urls
Author: UNKNOWN
Author-email: UNKNOWN
License: MIT
Keywords: django mptt urls hierarchy clean friendly
Platform: UNKNOWN
Classifier: Environment :: Web Environment
Classifier: Framework :: Django
Classifier: Intended Audience :: Developers
Classifier: License :: OSI Approved :: MIT License
Classifier: Operating System :: OS Independent
Classifier: Programming Language :: Python
Classifier: Programming Language :: Python :: 3.4
Classifier: Topic :: Internet :: WWW/HTTP
Classifier: Topic :: Internet :: WWW/HTTP :: Dynamic Content
Requires-Dist: django (>=1.7)
Requires-Dist: django-mptt (>=0.6.1)
